STEMTool-2024.12.21.dist-info/.ipynb_checkpoints/PKG-INFO-checkpoint
STEMTool-2024.12.21.dist-info/.ipynb_checkpoints/SOURCES-checkpoint.txt
STEMTool-2024.12.21.dist-info/.ipynb_checkpoints/dependency_links-checkpoint.txt
STEMTool-2024.12.21.dist-info/.ipynb_checkpoints/requires-checkpoint.txt
STEMTool-2024.12.21.dist-info/.ipynb_checkpoints/top_level-checkpoint.txt
stemtool/__init__.py
stemtool/timer.py
stemtool/afit/__init__.py
stemtool/afit/atom_positions.py
stemtool/afit/drift_corr.py
stemtool/dpc/__init__.py
stemtool/dpc/atomic_dpc.py
stemtool/dpc/dpc_utils.py
stemtool/dpc/nbed_dpc.py
stemtool/eels/__init__.py
stemtool/eels/eels_tools.py
stemtool/gpa/__init__.py
stemtool/gpa/gpa.py
stemtool/nbed/__init__.py
stemtool/nbed/nbed_strain.py
stemtool/sim/__init__.py
stemtool/sim/multislice.py
stemtool/util/__init__.py
stemtool/util/fourier_reg.py
stemtool/util/gauss_utils.py
stemtool/util/image_utils.py
stemtool/util/pnccd.py
stemtool/util/sobel_canny.py
STEMTool-2024.12.21.dist-info/LICENSE
STEMTool-2024.12.21.dist-info/METADATA
STEMTool-2024.12.21.dist-info/WHEEL
STEMTool-2024.12.21.dist-info/top_level.txt
STEMTool-2024.12.21.dist-info/RECORD
