Metadata-Version: 2.1
Name: STEMTool
Version: 2024.12.21
Summary: A single package for analyzing atomic resolution STEM, 4D-STEM and STEM-EELS datasets, along with basic STEM simulation functionality
Author-email: Debangshu Mukherjee <mukherjeed@ornl.gov>
Maintainer-email: Debangshu Mukherjee <mukherjeed@ornl.gov>
License: MIT License
Project-URL: Homepage, https://github.com/pycroscopy/stemtool
Project-URL: Issues, https://github.com/pycroscopy/stemtool/issues
Keywords: elecron microscopy,TEM,STEM,4D-STEM,STEM-EELS,Microscope Simulation
Classifier: Programming Language :: Python :: 3
Classifier: License :: OSI Approved :: MIT License
Classifier: Operating System :: OS Independent
Requires-Python: >=3.9
License-File: LICENSE
Requires-Dist: pywavelets>=0.5.2
Requires-Dist: numpy>=1.13.0
Requires-Dist: scipy>=1.0.0
Requires-Dist: matplotlib>=2.2.0
Requires-Dist: pillow>=10.1.0
Requires-Dist: scikit-image>=0.13.0
Requires-Dist: matplotlib-scalebar>=0.5.0
Requires-Dist: ase>=3.16.0
Requires-Dist: h5py>=3.7.0
Requires-Dist: dask>=2021.9.0
